{
	"type": "FeatureCollection",
	"features": [
		{
			"type": "Feature",
			"properties": {
				"name": "Caesar",
				"date": "Born 100 BC",
				"significance":"Roman dictator. He played a critical role in the demise of the Roman Republic and the rise of the Roman Empire.",
				"imageUrl":"/assets/images/backgrounds/markers/figures/BC1/caesar.jpg"
			},
			"geometry": {
				"coordinates": [
					12.468559639998972,
          41.895507187914745
				],
				"type": "Point"
			}
		}
	]
}