{
	"type": "FeatureCollection",
	"features": [
		{
			"type": "Feature",
			"properties": {
				"name": "Bill Clinton",
				"date": "Born August 19, 1946",
				"significance":"President of the USA",
				"imageUrl":"/assets/images/backgrounds/markers/figures/1994/clinton.jpg"
			},
			"geometry": {
				"coordinates": [
					-93.59,
          33.676389
				],
				"type": "Point"
			}
		}
	]
}